semper_brain4x_stt_utils/__init__.py
semper_brain4x_stt_utils/listener.py
semper_brain4x_stt_utils-0.0.6.dist-info/LICENSE
semper_brain4x_stt_utils-0.0.6.dist-info/METADATA
semper_brain4x_stt_utils-0.0.6.dist-info/WHEEL
semper_brain4x_stt_utils-0.0.6.dist-info/top_level.txt
semper_brain4x_stt_utils-0.0.6.dist-info/RECORD
