Metadata-Version: 2.1
Name: semper-brain4x-stt-utils
Version: 0.0.6
Summary: Package for continuously listening to raw audio.
Home-page: http://git.semper-tech.com/arcelik/semper-brain4x-stt-utils/
Author: Mehmet Uluc Sahin
Author-email: ulucsahin@gmail.com
License: UNKNOWN
Platform: UNKNOWN
Classifier: Programming Language :: Python :: 3
Classifier: License :: OSI Approved :: MIT License
Classifier: Operating System :: OS Independent
Requires-Python: >=3.6
